vardll/__init__.py
vardll/dllvariable.py
vardll/loader.py
vardll-1.5.4.dist-info/LICENSE
vardll-1.5.4.dist-info/METADATA
vardll-1.5.4.dist-info/WHEEL
vardll-1.5.4.dist-info/top_level.txt
vardll-1.5.4.dist-info/RECORD
