Metadata-Version: 2.2
Name: vardll
Version: 1.5.4
Summary: A library used to read uncompiled files and DLL files (Really useful)
Author-email: Universal CEO <universal.store.panel@gmail.com>
License: Custom License
Classifier: Programming Language :: Python :: 3
Classifier: License :: OSI Approved :: MIT License
Classifier: Operating System :: OS Independent
Requires-Python: >=3.6
License-File: LICENSE
